rliable/__init__.py
rliable/library.py
rliable/metrics.py
rliable/plot_utils.py
rliable-1.0.8.dist-info/LICENSE
rliable-1.0.8.dist-info/METADATA
rliable-1.0.8.dist-info/WHEEL
rliable-1.0.8.dist-info/top_level.txt
rliable-1.0.8.dist-info/RECORD
