Metadata-Version: 2.1
Name: rliable
Version: 1.0.8
Summary: rliable: Reliable evaluation on reinforcement learning and machine learning benchmarks.
Home-page: https://github.com/google-research/rliable
Author: Rishabh Agarwal
License: Apache 2.0
Project-URL: Documentation, https://github.com/google-research/rliable
Project-URL: Bug Reports, https://github.com/google-research/rliable/issues
Project-URL: Source, https://github.com/google-research/rliable
Keywords: benchmarking,evaluation,reproducibility,research,reinforcement,machine,learning,research
Classifier: Development Status :: 4 - Beta
Classifier: Intended Audience :: Developers
Classifier: Intended Audience :: Education
Classifier: Intended Audience :: Science/Research
Classifier: License :: OSI Approved :: Apache Software License
Classifier: Programming Language :: Python :: 3
Classifier: Programming Language :: Python :: 3.5
Classifier: Programming Language :: Python :: 3.6
Classifier: Programming Language :: Python :: 3.7
Classifier: Programming Language :: Python :: 3.8
Classifier: Programming Language :: Python :: 3 :: Only
Classifier: Topic :: Scientific/Engineering
Classifier: Topic :: Scientific/Engineering :: Mathematics
Classifier: Topic :: Scientific/Engineering :: Artificial Intelligence
Classifier: Topic :: Software Development
Classifier: Topic :: Software Development :: Libraries
Classifier: Topic :: Software Development :: Libraries :: Python Modules
License-File: LICENSE
Requires-Dist: arch (==5.3.0)
Requires-Dist: scipy (>=1.7.0)
Requires-Dist: absl-py (>=0.9.0)
Requires-Dist: numpy (>=1.16.4)
Requires-Dist: seaborn (>=0.11.2)
